Sum_SB2_04905/__init__.py
Sum_SB2_04905-0.0.1.dist-info/Licence.txt
Sum_SB2_04905-0.0.1.dist-info/METADATA
Sum_SB2_04905-0.0.1.dist-info/WHEEL
Sum_SB2_04905-0.0.1.dist-info/top_level.txt
Sum_SB2_04905-0.0.1.dist-info/RECORD
